CIRI_long/__init__.py
CIRI_long/align.py
CIRI_long/collapse.py
CIRI_long/env.py
CIRI_long/find_bsj.py
CIRI_long/find_ccs.py
CIRI_long/logger.py
CIRI_long/main.py
CIRI_long/utils.py
CIRI_long/version.py
libs/__init__.py
libs/striped_smith_waterman/__init__.py
libs/striped_smith_waterman/libssw.so
libs/striped_smith_waterman/pyssw.py
libs/striped_smith_waterman/ssw_wrap.py
CIRI_long-1.1.0.dist-info/LICENSE
CIRI_long-1.1.0.dist-info/METADATA
CIRI_long-1.1.0.dist-info/WHEEL
CIRI_long-1.1.0.dist-info/entry_points.txt
CIRI_long-1.1.0.dist-info/top_level.txt
CIRI_long-1.1.0.dist-info/RECORD
