Metadata-Version: 2.1
Name: CIRI-long
Version: 1.1.0
Summary: circular RNA identification from Nanopore
Home-page: https://github.com/bioinfo-biols/CIRI-long
Author: Jinyang Zhang
Author-email: zhangjinyang@biols.ac.cn
Maintainer: Jinyang Zhang
Maintainer-email: zhangjinyang@biols.ac.cn
License: MIT
Keywords: circRNA
Platform: UNKNOWN
Classifier: License :: OSI Approved :: MIT License
Classifier: Programming Language :: Python
Classifier: Intended Audience :: Developers
Classifier: Operating System :: OS Independent
Requires-Python: >3.7.0
License-File: LICENSE
Requires-Dist: argparse (>=1.2.1)
Requires-Dist: Cython (>=0.29.13)
Requires-Dist: mappy (>=2.17)
Requires-Dist: numpy (>=1.17.0)
Requires-Dist: pandas (>=0.25.0)
Requires-Dist: pysam (>=0.15.3)
Requires-Dist: python-Levenshtein (>=0.12.1)
Requires-Dist: scikit-learn (>=0.21.3)
Requires-Dist: scipy (>=1.3.1)
Requires-Dist: biopython (>=1.76)
Requires-Dist: pyspoa (>=0.0.5)
Requires-Dist: bwapy (>=0.1.4)
Requires-Dist: edlib (>=1.3.9)
Requires-Dist: pyccs (>=1.1.0)
